scine_database/LICENSE.txt
scine_database/__init__.py
scine_database/compound_and_flask_creation.py
scine_database/concentration_query_functions.py
scine_database/energy_query_functions.py
scine_database/insert_concentration.py
scine_database/libcore.so
scine_database/libdatabase.so
scine_database/libutilsos.so
scine_database/queries.py
scine_database/scine_database.cpython-310-x86_64-linux-gnu.so
scine_database/test_database_setup.py
scine_database.libs/libboost_atomic-00e6ede8.so.1.78.0
scine_database.libs/libboost_filesystem-e9e1d9ac.so.1.78.0
scine_database.libs/libboost_system-c0fa27da.so.1.78.0
scine_database.libs/libbson-1-d8ae3d97.0.so.0.0.0
scine_database.libs/libbsoncxx-5a1a149f.so.3.7.2
scine_database.libs/libcrypto-bdaed0ea.so.1.1.1k
scine_database.libs/libgomp-e985bcbb.so.1.0.0
scine_database.libs/libmongoc-1-2e878969.0.so.0.0.0
scine_database.libs/libmongocxx-e72f447e.so.3.7.2
scine_database.libs/libssl-60250281.so.1.1.1k
scine_database.libs/libutilsos-1a1c26a4.so
scine_database-1.5.0.dist-info/METADATA
scine_database-1.5.0.dist-info/WHEEL
scine_database-1.5.0.dist-info/top_level.txt
scine_database-1.5.0.dist-info/RECORD
